cc2538/__init__.py
cc2538-2.1.0.dist-info/DESCRIPTION.rst
cc2538-2.1.0.dist-info/METADATA
cc2538-2.1.0.dist-info/RECORD
cc2538-2.1.0.dist-info/WHEEL
cc2538-2.1.0.dist-info/metadata.json
cc2538-2.1.0.dist-info/top_level.txt
