Metadata-Version: 2.0
Name: cc2538
Version: 2.1.0
Summary: TI CC13xx/CC2538/CC26xx Serial Boot Loader.
Home-page: https://github.com/JelmerT/cc2538-bsl
Author: Jelmer Tiete
Author-email: jelmer@tiete.be
License: ISC
Platform: UNKNOWN
Classifier: License :: OSI Approved :: MIT License
Classifier: Programming Language :: Python
Classifier: Programming Language :: Python :: 2.6
Classifier: Programming Language :: Python :: 2.7
Requires-Dist: intelhex
Requires-Dist: pyserial
Requires-Dist: python-magic
Requires-Dist: scripttest
